ffxivicongetter/__init__.py
ffxivicongetter/__main__.py
ffxivicongetter/cli.py
ffxivicongetter/core.py
ffxivicongetter/jobs.py
ffxivicongetter/py.typed
ffxivicongetter-0.2.0.dist-info/METADATA
ffxivicongetter-0.2.0.dist-info/WHEEL
ffxivicongetter-0.2.0.dist-info/entry_points.txt
ffxivicongetter-0.2.0.dist-info/licenses/LICENSE.md
ffxivicongetter-0.2.0.dist-info/RECORD
