Metadata-Version: 2.4
Name: ffxivicongetter
Version: 0.2.0
Summary: Add your description here
Author-email: Dowon <ks2515@naver.com>
License-File: LICENSE.md
Requires-Python: >=3.11
Requires-Dist: hishel[httpx]
Requires-Dist: httpx[http2,zstd]
Requires-Dist: tqdm
